PyScrawl-1.2.dist-info/DESCRIPTION.rst
PyScrawl-1.2.dist-info/METADATA
PyScrawl-1.2.dist-info/RECORD
PyScrawl-1.2.dist-info/WHEEL
PyScrawl-1.2.dist-info/metadata.json
PyScrawl-1.2.dist-info/top_level.txt
pyscrawl/__init__.py
